{
    "version": 2,
    "tags": [
        {
            "name": "xtal-frappe-chart",
            "description": "Web component wrapper around the cool Frappe chart (https://frappe.io/charts) library.",
            "jsDoc": "/**\n * Web component wrapper around the cool Frappe chart (https://frappe.io/charts) library.\n * @element xtal-frappe-chart\n * @event selected-element-changed - fires when user selects chart data element\n */",
            "attributes": [],
            "properties": [
                {
                    "name": "val",
                    "type": "\"set\" | \"remove\""
                },
                {
                    "name": "disabled",
                    "type": "boolean"
                },
                {
                    "name": "evCount",
                    "type": "{ [key: string]: number; }"
                },
                {
                    "name": "asIs",
                    "type": "\"\" | \"-changed\""
                },
                {
                    "name": "data",
                    "description": "Data to chart",
                    "jsDoc": "/**\n     * Data to chart\n     */",
                    "type": "any",
                    "testValues": {
                        "test1": {
                            "title": "My Awesome Chart",
                            "data": {
                                "labels": [
                                    "12am-3am",
                                    "3am-6am",
                                    "6am-9am",
                                    "9am-12pm",
                                    "12pm-3pm",
                                    "3pm-6pm",
                                    "6pm-9pm",
                                    "9pm-12am"
                                ],
                                "datasets": [
                                    {
                                        "name": "Some Data",
                                        "color": "light-blue",
                                        "values": [
                                            25,
                                            40,
                                            30,
                                            35,
                                            8,
                                            52,
                                            17,
                                            -4
                                        ]
                                    },
                                    {
                                        "name": "Another Set",
                                        "color": "violet",
                                        "values": [
                                            25,
                                            50,
                                            -10,
                                            15,
                                            18,
                                            32,
                                            27,
                                            14
                                        ]
                                    },
                                    {
                                        "name": "Yet Another",
                                        "color": "blue",
                                        "values": [
                                            15,
                                            20,
                                            -3,
                                            -15,
                                            58,
                                            12,
                                            -17,
                                            37
                                        ]
                                    }
                                ]
                            },
                            "type": "bar",
                            "height": 250,
                            "isNavigable": true
                        }
                    }
                },
                {
                    "name": "newDataPoint",
                    "description": "Add new data point to chart",
                    "jsDoc": "/**\n     * Add new data point to chart\n     *\n     */",
                    "type": "any"
                },
                {
                    "name": "staleDataPoint",
                    "description": "Remove data point from chart",
                    "jsDoc": "/**\n     * Remove data point from chart\n     */",
                    "type": "any"
                },
                {
                    "name": "updateData",
                    "description": "Update Data",
                    "jsDoc": "/**\n     * Update Data\n     */",
                    "type": "any"
                }
            ],
            "events": [
                {
                    "name": "selected-element-changed",
                    "description": "Fired when user selects chart element",
                    "detail": [
                        {
                            "name": "value",
                            "description": "Value of selected Element",
                            "type": "SelectedElementEventDetail"
                        }
                    ],
                    "testExpectedValues": {
                        "test1": {
                            "value": {
                                "values": [
                                    -4,
                                    14,
                                    37
                                ],
                                "label": "9pm-12am",
                                "index": 7
                            }
                        }
                    }
                }
            ],
            "slots": [],
            "selfResolvingModulePath": "https://cdn.pika.dev/xtal-frappe-chart"
        }
    ]
}